kkbtools/LICENSE
kkbtools/VERSION
kkbtools/__init__.py
kkbtools/__main__.py
kkbtools/common.py
kkbtools/tools.py
kkbtools-0.1.5.dist-info/LICENSE
kkbtools-0.1.5.dist-info/METADATA
kkbtools-0.1.5.dist-info/WHEEL
kkbtools-0.1.5.dist-info/entry_points.txt
kkbtools-0.1.5.dist-info/top_level.txt
kkbtools-0.1.5.dist-info/zip-safe
kkbtools-0.1.5.dist-info/RECORD
