Metadata-Version: 2.1
Name: kkbtools
Version: 0.1.5
Summary: 爬虫业务中，常用的工具集
Home-page: https://github.com/haidongsong/kkbtools
Author: dylan
Author-email: shddylan@163.com
License: MIT
Keywords: kkb tools kkbtools
Platform: any
Classifier: Programming Language :: Python :: 3
Classifier: License :: OSI Approved :: MIT License
Requires-Python: >=3.6
License-File: LICENSE
Requires-Dist: feapder
Requires-Dist: oss2
Requires-Dist: requests
Requires-Dist: pandas
Requires-Dist: pymongo
Requires-Dist: PyMySQL
Requires-Dist: python-dateutil
Requires-Dist: tqdm
Requires-Dist: urllib3
Requires-Dist: XlsxWriter
